pickson2/__init__.py
pickson2/pickson2.py
pickson2-1.0.0.dist-info/LICENSE
pickson2-1.0.0.dist-info/METADATA
pickson2-1.0.0.dist-info/WHEEL
pickson2-1.0.0.dist-info/top_level.txt
pickson2-1.0.0.dist-info/RECORD
